Workbook

Sheet Sheet1
A1: Living Room
A2: Item Category | B2: Description | C2: Brand | D2: Finish/Color | E2: Unit | F2: Qty | G2: Rate | H2: Amount | I2: Remarks
A3: TV Unit Back Panel | E3: Sqft | F3: 106 | G3: 450 | H3: =F3*G3 -> 47700
A4: center table | E4: Dimension | F4: 5'x3' | H4: 25000
A5: Side table | E5: Dimension | F5: 6'3"x1'6"
A6: Drawer | E6: no's | F6: 4 | G6: 9500 | H6: =G6*F6 -> 38000
A7: Tall open box | E7: sqft | F7: 30 | G7: 550 | H7: =G7*F7 -> 16500
A8: Sofa back panel | E8: sqft | F8: 123 | G8: 350 | H8: =G8*F8 -> 43050
A9: window grill | E9: sqft | F9: 1 | G9: 18500 | H9: =G9*F9 -> 18500
A10: Partition Wooden | E10: sqft | F10: 36 | G10: 250 | H10: =G10*F10 -> 9000
A12: Kitchen
A13: L shape base unit carcass wuth Shutter | E13: Sqft | F13: 32 | G13: 1850 | H13: =G13*F13 -> 59200
A14: L shape box wall carcuss | E14: Sqft | F14: 41 | G14: 1650 | H14: =G14*F14 -> 67650
A15: U shape over head f&s | E15: Sqft | F15: 26 | G15: 1650 | H15: =G15*F15 -> 42900
A16: Base unit carcuss | E16: Sqft | F16: 9 | G16: 1650 | H16: =G16*F16 -> 14850
A17: Wall unit carcuss | E17: Sqft | F17: 12 | G17: 1650 | H17: =G17*F17 -> 19800
A18: counter top and backsplash | E18: Count | F18: 5 | G18: 9500 | H18: =G18*F18 -> 47500
A19: Lounge Area | E19: sqft | F19: 74 | G19: 650 | H19: =G19*F19 -> 48100
A20: L Shape Paneling | E20: sqft | H20: =G20*F20 -> 0
A21: Puja Backside Pantry Storage with arch | E21: sqft | F21: 55 | G21: 1650 | H21: =G21*F21 -> 90750
A22: Guest bed room
A23: Wardrobe | E23: Sqft | F23: 125 | G23: 1350 | H23: =F23*G23 -> 168750
A24: Overhead f&s | E24: Sqft | F24: 25 | G24: 1050 | H24: =F24*G24 -> 26250
A25: Door side wardrobe | E25: Sqft | F25: 48 | G25: 1350 | H25: =F25*G25 -> 64800
A26: Overhead f&s | E26: Sqft | F26: 15 | G26: 1050 | H26: =F26*G26 -> 15750
A27: Bed back side panel | E27: Sqft | F27: 103 | G27: 350 | H27: =F27*G27 -> 36050
A28: Side table | E28: no's | F28: 1 | G28: 11500 | H28: =F28*G28 -> 11500
A30: Kids bed room
A31: Wardrobe | E31: Sqft | F31: 95 | G31: 1350 | H31: =F31*G31 -> 128250
A32: loft | E32: Sqft | F32: 25 | G32: 1050 | H32: =F32*G32 -> 26250
A33: side table | E33: no's | F33: 1 | G33: 12500 | H33: =F33*G33 -> 12500
A34: bed back side panel | E34: Sqft | F34: 115 | G34: 400 | H34: =F34*G34 -> 46000
A35: Dressing area | E35: Sqft | F35: 20 | G35: 950 | H35: =F35*G35 -> 19000
A36: Bay window storage unit | E36: Sqft | F36: 25 | G36: 950 | H36: =F36*G36 -> 23750
A37: Bed Side Bookrack with Glass Doors | E37: Sqft | F37: 30 | G37: 850 | H37: =F37*G37 -> 25500
A38: loft | E38: Sqft | F38: 25 | G38: 1350 | H38: =F38*G38 -> 33750
A41: Master bed room
A42: wardrobe | E42: Sqft | F42: 135 | G42: 1350 | H42: =F42*G42 -> 182250
A43: Base unit L Shape | E43: no's | F43: 1 | G43: 16500 | H43: =F43*G43 -> 16500
A44: drawer | E44: Sqft | F44: 1 | G44: 13500 | H44: =F44*G44 -> 13500
A45: Study Table Hanging | E45: Sqft | F45: 1 | G45: 25000 | H45: =F45*G45 -> 25000
A46: tv unit wall panel | E46: Sqft | F46: 45 | G46: 400 | H46: =F46*G46 -> 18000
A47: Pooja unit
A48: Storage | E48: sqft | F48: 15 | G48: 1350 | H48: =F48*G48 -> 20250
A49: wall panel | E49: sqft | F49: 36 | G49: 450 | H49: =F49*G49 -> 16200
A50: Door | E50: sqft | F50: 95 | G50: 1500 | H50: =F50*G50 -> 142500
A51: Balcony
A52: Deck flooring | E52: sqft | F52: 68 | G52: 350 | H52: 0
A53: Vertical grass panel | E53: sqft | F53: 100 | G53: 850 | H53: 0
A54: L shape sitout | E54: sqft | F54: 30 | G54: 950 | H54: =F54*G54 -> 28500
A55: Tulasi kota base | E55: sqft | F55: 1 | G55: 25000 | H55: 0
A56: cornor unit | E56: sqft | F56: 20 | G56: 1250 | H56: =F56*G56 -> 25000
A57: Crockery with wash basin
A58: Base unit | E58: Sqft | F58: 20 | G58: 1350 | H58: =F58*G58 -> 27000
A59: Open box | E59: Sqft | F59: 25 | G59: 950 | H59: =F59*G59 -> 23750
A60: counter top | E60: count | F60: 1 | G60: 12500 | H60: =F60*G60 -> 12500
A61: Mirror Hatching | E61: sqft | F61: 25 | G61: 450 | H61: =F61*G61 -> 11250
A62: Utility
A63: base unit | E63: sqft | F63: 25 | G63: 1250 | H63: =F63*G63 -> 31250
A64: wall unit | E64: sqft | F64: 45 | G64: 1050 | H64: =F64*G64 -> 47250
A65: counter top and backsplash | E65: sqft | F65: 85 | G65: 250 | H65: =F65*G65 -> 21250
A66: Ceiling
A67: Total | E67: sqft | F67: 2195 | G67: 80 | H67: =F67*G67 -> 175600
A68: Lights
A69: panel lights | E69: nos | F69: 45 | G69: 950 | H69: =F69*G69 -> 42750
A70: profile lights | E70: feets | F70: 46 | G70: 650 | H70: =F70*G70 -> 29900
A71: spot lights | E71: nos | F71: 45 | G71: 350 | H71: =F71*G71 -> 15750
A72: Cabinet Lights | E72: nos | F72: 90 | G72: 250 | H72: =F72*G72 -> 22500
A73: Curtains
A74: living room | E74: sqft | F74: 76 | G74: 300 | H74: =F74*G74 -> 22800
A75: master bed room | E75: sqft | F75: 46 | G75: 300 | H75: =F75*G75 -> 13800
A76: kids bed room | E76: sqft | F76: 44 | G76: 300 | H76: =F76*G76 -> 13200
A77: guest bed room | E77: sqft | F77: 76 | G77: 300 | H77: =F77*G77 -> 22800
A78: balcony | E78: sqft | F78: 59 | G78: 300 | H78: =F78*G78 -> 17700
H79: =F79*G79 -> 0
A80: putting paint with primer | E80: sqft | F80: 1 | G80: 85000 | H80: =F80*G80 -> 85000
A81: civil work | F81: 1 | G81: 45000 | H81: =F81*G81 -> 45000
A84: Total | H84: =SUM(H3:H81) -> 2395350
H85: 23.5

Sheet Sheet3
A1: Furniture
A2: MBR BED | E2: dimensions | F2: 6'x5'6" | G2: 45000 | H2: =G2 -> 45000
A3: dinning chairs | E3: nos | F3: 6 | G3: 15000 | H3: =F3*G3 -> 90000
A4: L shape sofa | E4: Dimension | F4: 11'x7'.5" | G4: 105000 | H4: =G4 -> 105000
A5: dressing chair | E5: nos | F5: 2 | G5: 13500 | H5: =F5*G5 -> 27000
A6: study chair | E6: nos | F6: 1 | G6: 10500 | H6: =F6*G6 -> 10500
A7: kitchen sink | E7: nos | F7: 2 | G7: 9500 | H7: =F7*G7 -> 19000
A8: Wash basin | E8: nos | F8: 1 | G8: 12500 | H8: =F8*G8 -> 12500
A9: Hanging swing chair | E9: nos | F9: 1 | G9: 35000 | H9: =F9*G9 -> 35000
A10: Dressing Mirrors | E10: nos | F10: 3 | G10: 18500 | H10: =F10*G10 -> 55500
A11: handing lamps | E11: nos | F11: 3 | G11: 8500 | H11: =F11*G11 -> 25500
A13: Total | H13: =sum(H2:H11) -> 425000

Sheet Sheet1 (1)
B1: Living Room
B2: Item Category | C2: Description | D2: Brand | E2: Finish/Color | F2: Unit | G2: Qty | H2: Rate | I2: Amount | J2: Remarks | K2: RRK
B3: TV Unit Back Panel | F3: Sqft | G3: 106 | H3: 450 | I3: =G3*H3 -> 47700 | J3: Different prices were used for TV & Sofa | K3: =G3*350 -> 37100 | L3: 1.2mm laminate ( box paneling )
K4: 15000
B5: Side table | F5: Dimension | G5: 6'3"x1'6"
B6: Drawer | F6: no's | G6: 4 | H6: 9500 | I6: =H6*G6 -> 38000 | K6: =G6*7500 -> 30000
B7: Tall open box | F7: sqft | G7: 30 | H7: 550 | I7: =H7*G7 -> 16500 | K7: =G7*450 -> 13500
B8: Sofa back panel | F8: sqft | G8: 123 | H8: 350 | I8: =H8*G8 -> 43050 | J8: PVC | K8: =G8*350 -> 43050 | L8: 0.8 laminate | M8: 18500 | N8: =K8-M8 -> 24550
B9: window grill | F9: sqft | G9: 1 | H9: 18500 | I9: 0 | J9: In absence of material specification, difficult to validate the price quoted | K9: 12000 | L9: after design we can finalise
B10: TOTAL | I10: =SUM(I3:I9) -> 145250 | K10: =SUM(K3:K9) -> 150650
B11: Kitchen
B12: L shape base unit carcuss | F12: Sqft | G12: 32 | H12: 1850 | I12: =H12*G12 -> 59200 | J12: 12-15% high even if IS 710 ply is used | K12: =G12*1650 -> 52800
B13: L shape box wall carcuss | F13: Sqft | G13: 41 | H13: 1650 | I13: =H13*G13 -> 67650 | J13: Chimney needs to be included. Material of counter top, daddo tiles need to be specified | K13: =G13*1400 -> 57400
B14: U shape over head f&s | F14: Sqft | G14: 26 | H14: 1650 | I14: =H14*G14 -> 42900 | K14: =G14*1400 -> 36400
B15: Base unit carcuss | F15: Sqft | G15: 9 | H15: 1650 | I15: =H15*G15 -> 14850 | K15: =G15*1500 -> 13500
B16: Wall unit carcuss | F16: Sqft | G16: 12 | H16: 1650 | I16: =H16*G16 -> 19800 | J16: I guess this means pantry unit. Confirm whether pantry unit is included. Please specify no.of baskets/trys etc | K16: =G16*1450 -> 17400
B17: counter top and backsplash | F17: Count | G17: 5 | H17: 9500 | I17: =H17*G17 -> 47500 | J17: Wash basin too should have been part of this. | K17: =G17*8500 -> 42500
B18: Lounge Area | F18: sqft | G18: 74 | H18: 650 | I18: =H18*G18 -> 48100 | K18: =G18*500 -> 37000
B19: TOTAL | I19: =SUM(I12:I18) -> 300000 | K19: =SUM(K12:K18) -> 257000
B20: Guest bed room
B21: Wardrobe | F21: Sqft | G21: 125 | H21: 1350 | I21: =G21*H21 -> 168750 | K21: =G21*1200 -> 150000
B22: Overhead f&s | F22: Sqft | G22: 25 | H22: 1050 | I22: =G22*H22 -> 26250 | K22: =G22*900 -> 22500
B23: Door side wardrobe | F23: Sqft | G23: 48 | H23: 1350 | I23: =G23*H23 -> 64800 | K23: =G23*1200 -> 57600
B24: Overhead f&s | F24: Sqft | G24: 15 | H24: 1050 | I24: =G24*H24 -> 15750 | J24: Overhead F&S for Door backside can be removed | K24: =G24*950 -> 14250
B25: Bed back side panel | F25: Sqft | G25: 103 | H25: 350 | I25: =G25*H25 -> 36050 | J25: Premium wallpaper adequate/Can be discussed | K25: =G25*200 -> 20600
B26: Side table designs sjinteriorsdnd | F26: no's | G26: 3 | H26: 11500 | I26: =G26*H26 -> 34500 | J26: Logic for 3 nos is unclear. SJ to clarify | K26: 15000
B27: TOTAL | I27: =SUM(I21:I26) -> 346100 | K27: =SUM(K21:K26) -> 279950
B28: Kids bed room
B29: Wardrobe | F29: Sqft | G29: 55 | H29: 1350 | I29: =G29*H29 -> 74250 | K29: =G29*1200 -> 66000 | L29: As per design should revise SJ Interiors DnD
B30: loft | F30: Sqft | G30: 18 | H30: 1050 | I30: =G30*H30 -> 18900 | J30: Loft/Overhead F&S of KBR and GBR shall be same | K30: =G30*950 -> 17100
B31: side table designs sjinteriorsdnd | F31: no's | G31: 2 | H31: 12500 | I31: =G31*H31 -> 25000 | J31: A desk with one drawer/open draw is enough eitherside | K31: =G31*6500 -> 13000
B32: bed backside panel | F32: Sqft | G32: 115 | H32: 400 | I32: =G32*H32 -> 46000 | J32: Same back panel price to be mentioned everywhere | K32: =G32*300 -> 34500
B33: Dressing area | F33: Sqft | G33: 38 | H33: 950 | I33: =G33*H33 -> 36100 | J33: Very high. | K33: =G33*750 -> 28500
B34: Bay window storage unit | F34: Sqft | G34: 25 | H34: 950 | I34: =G34*H34 -> 23750 | J34: This should include cushion | K34: =G34*900 -> 22500
B35: Tall open box | F35: Sqft | G35: 15 | H35: 850 | I35: =G35*H35 -> 12750 | J35: 550 was quoted above for tall open box | K35: =G35*550 -> 8250
B36: wardrobe | F36: Sqft | G36: 45 | H36: 1350 | I36: =G36*H36 -> 60750 | J36: Where is the 2nd wardrobe | K36: =G36*1200 -> 54000
B37: loft | F37: Sqft | G37: 25 | H37: 1350 | I37: =G37*H37 -> 33750 | J37: Loft price for similar work shall be same | K37: =G37*950 -> 23750
B38: TOTAL | I38: =SUM(I29:I37) -> 331250 | K38: =SUM(K29:K37) -> 267600
B39: Master bed room
B40: wardrobe | F40: Sqft | G40: 95 | H40: 1350 | I40: =G40*H40 -> 128250 | J40: Shift dressing table to north wall beside TV panel | K40: =G40*1200 -> 114000 | L40: As per design should revise
B41: Bedside Book rack with Glass doors | F41: Sqft | G41: 15 | H41: 1350 | I41: =G41*H41 -> 20250 | K41: =G41*1100 -> 16500
B42: drawer | F42: Sqft | G42: 4 | H42: 11500 | I42: =G42*H42 -> 46000 | J42: Reason for 4 nos drawers is NOT clear
B43: bay window | F43: Sqft | G43: 30 | H43: 1350 | I43: =G43*H43 -> 40500 | K43: =G43*1150 -> 34500
B44: tv unit wall panel | F44: Sqft | G44: 115 | H44: 400 | I44: =G44*H44 -> 46000 | J44: 115 sft can be reduced to 50 | K44: =50*350 -> 17500
B45: TOTAL | I45: =SUM(I40:I44) -> 281000 | K45: =SUM(K40:K44) -> 182500
B46: Pooja unit
B47: Storage | F47: sqft | G47: 15 | H47: 1350 | I47: =G47*H47 -> 20250 | K47: =G47*1200 -> 18000
B48: wall panel | F48: sqft | G48: 36 | H48: 450 | I48: =G48*H48 -> 16200 | J48: Higher price of Rs 400 was retained | K48: =G48*400 -> 14400
B49: Door | F49: sqft | G49: 95 | H49: 1500 | I49: =G49*H49 -> 142500 | K49: =G49*1400 -> 133000
B50: TOTAL | I50: =SUM(I47:I49) -> 178950 | K50: =SUM(K47:K49) -> 165400
B51: Balcony
B52: Deck flooring | F52: sqft | G52: 68 | H52: 350 | J52: Not required
B53: Vertical grass panel | F53: sqft | G53: 100 | H53: 850 | J53: Not required/Value for money option can be suggested
B54: L shape sitout | F54: sqft | G54: 30 | H54: 950 | I54: =G54*H54 -> 28500 | K54: =G54*950 -> 28500
B55: Tulasi kota base | F55: sqft | G55: 1 | H55: 25000 | J55: Not required. Simple version to be explored | L55: at that stage we can purchase standalone
B56: cornor unit | F56: sqft | G56: 20 | H56: 1250 | I56: =G56*H56 -> 25000 | K56: =G56*1200 -> 24000
B57: TOTAL | I57: =SUM(I52:I56) -> 53500 | K57: =SUM(K52:K56) -> 52500
B58: Crockery with wash basin
B59: Base unit | F59: Sqft | G59: 20 | H59: 1350 | I59: =G59*H59 -> 27000 | K59: =G59*1200 -> 24000
B60: Open box | F60: Sqft | G60: 25 | H60: 950 | I60: =G60*H60 -> 23750 | K60: =G60*900 -> 22500
B61: counter top | F61: count | G61: 1 | H61: 12500 | I61: =G61*H61 -> 12500 | K61: =12000 -> 12000
B62: Mirror Hatching | F62: sqft | G62: 25 | H62: 400 | I62: =G62*H62 -> 10000 | J62: Aesthetic mirror without hatching also is okay | K62: =G62*450 -> 11250
B63: TOTAL | I63: =SUM(I59:I62) -> 73250 | K63: =SUM(K59:K62) -> 69750
B64: Utility
B65: base unit | F65: sqft | G65: 25 | H65: 1250 | I65: =G65*H65 -> 31250 | J65: Original discussion was subsequently changed to two countertops to accommodate washing machine and dish washer on either side, in addition to cylinders. Estimate need to be revisited to account for the revised design designs sjinteriorsdnd | K65: =G65*H65 -> 31250
B66: wall unit | F66: sqft | G66: 45 | H66: 1050 | I66: =G66*H66 -> 47250 | K66: =G66*950 -> 42750
B67: counter top and backsplash | F67: sqft | G67: 85 | H67: 250 | I67: =G67*H67 -> 21250 | K67: =I67 -> 21250
B68: TOTAL | I68: =SUM(I65:I67) -> 99750 | K68: =SUM(K65:K67) -> 95250
B69: Ceiling
B70: Total | F70: sqft | G70: 2025 | H70: 80 | I70: =G70*H70 -> 162000 | J70: Ceiling SFT calculation needs to be checked designs sjinteriorsdnd | K70: =2200*H70 -> 176000
B71: Lights
B72: panel lights | F72: nos | G72: 45 | H72: 950 | I72: =G72*H72 -> 42750 | K72: =I72 -> 42750
B73: profile lights | F73: feets | G73: 46 | H73: 650 | I73: =G73*H73 -> 29900 | K73: =I73 -> 29900
B74: spot lights | F74: nos | G74: 45 | H74: 350 | I74: =G74*H74 -> 15750 | K74: =I74 -> 15750
B75: Cabinet Lights | F75: nos | G75: 90 | H75: 250 | I75: =G75*H75 -> 22500 | K75: =I75 -> 22500
B76: TOTAL | I76: =SUM(I72:I75) -> 110900 | J76: Does this include cable costs also | K76: =SUM(K72:K75) -> 110900
B77: Curtains
B78: living room | F78: sqft | G78: 76 | H78: 300 | I78: =G78*H78 -> 22800 | J78: Since dimensions and model and type are not yet known, original proposal numbers were left as it is. However, let this be based on actuals rather than part of the quote. | K78: =I78 -> 22800
B79: master bed room | F79: sqft | G79: 46 | H79: 300 | I79: =G79*H79 -> 13800 | K79: =I79 -> 13800
B80: kids bed room | F80: sqft | G80: 44 | H80: 300 | I80: =G80*H80 -> 13200 | K80: =I80 -> 13200
B81: guest bed room | F81: sqft | G81: 76 | H81: 300 | I81: =G81*H81 -> 22800 | K81: =I81 -> 22800
B82: balcony | F82: sqft | G82: 59 | H82: 300 | I82: =G82*H82 -> 17700 | K82: =I82 -> 17700
B83: Partition glass in wash rooms | I83: =G83*H83 -> 0 | J83: Specify the price. Can be decided later
B84: TOTAL | I84: =SUM(I78:I83) -> 90300 | K84: =SUM(K78:K83) -> 90300
B85: Miscellaneous works
B86: putting paint with primer | F86: sqft | G86: 1 | H86: 85000 | I86: =G86*H86 -> 85000 | K86: =I86 -> 85000
B87: civil work | G87: 1 | H87: 45000 | I87: =G87*H87 -> 45000 | K87: =I87 -> 45000
B88: Front elevation minimalist design | I88: ????
B89: TOTAL | I89: =SUM(I86:I88) -> 130000 | K89: =SUM(K86:K88) -> 130000
B90: Total | I90: =I89+I84+I76+I70+I68+I63+I57+I50+I45+I38+I27+I19+I10 -> 2302250 | J90: Total Interior works | K90: =K89+K84+K76+K68+K63+K57+K50+K45+K38+K27+K19+K10+K70-K84 -> 1937500
J91: Furniture | K91: ='Sheet3 (1)'!I13 -> 286000
J92: Grand Total | K92: =K90+K91 -> 2223500
B94: The following items are not clear in the estimate
B95: Pest control
B96: Plumbing part
B97: Material specification of All wood and hardware items like ply,laminate,WPC,hinges,kitches baskets,other hardware items,electrical cables,LED lights,channels,Ceiling, paints, locks etc is not mentioned
B98: Gas pipeline
B99: Deep cleaning
B100: Chimney
B101: Shoe rack
...

Sheet Summary
A3: S No | B3: Name of the unit | C3: SJ Price | D3: RRK offer | E3: Remarks | F3: Furniture | G3: SJ | H3: RRK
A4: 1 | B4: Living room | C4: ='Sheet1 (1)'!I10 -> 145250 | D4: ='Sheet1 (1)'!K10 -> 150650 | F4: MBR BED | G4: 45000 | H4: =G4 -> 45000
A5: 2 | B5: Kitchen | C5: ='Sheet1 (1)'!I19 -> 300000 | D5: ='Sheet1 (1)'!K19 -> 257000 | E5: Chiney shall be included on the proposal. Ideally Kitchen sink shall be part of quote | F5: dinning chairs | G5: 90000 | H5: =6*7500 -> 45000
A6: 3 | B6: Guest bed room | C6: ='Sheet1 (1)'!I27 -> 346100 | D6: ='Sheet1 (1)'!K27 -> 279950 | E6: Needs clarity on 3 nos side tables | F6: L shape sofa | G6: 105000 | H6: =90000 -> 90000
A7: 4 | B7: Kids Bed room | C7: ='Sheet1 (1)'!I38 -> 331250 | D7: ='Sheet1 (1)'!K38 -> 267600 | E7: Different prcies were used fro the same work at different places | F7: study chair | G7: 10500 | H7: 8000
A8: 5 | B8: Master bedroom | C8: ='Sheet1 (1)'!I45 -> 281000 | D8: ='Sheet1 (1)'!K45 -> 182500 | E8: Reason for 4 nos drawers is NOT clear | F8: kitchen sink | G8: 19000 | H8: =2*9500 -> 19000
A9: 6 | B9: Pooja unit | C9: ='Sheet1 (1)'!I50 -> 178950 | D9: ='Sheet1 (1)'!K50 -> 165400 | F9: Hanging swing chair | G9: 35000
A10: 7 | B10: Balcony | C10: ='Sheet1 (1)'!I57 -> 53500 | D10: ='Sheet1 (1)'!K57 -> 52500 | E10: Removed vertical grass panel and modified Tulasi kota requirement | F10: Dressing Mirrors | G10: 55500 | H10: =3*10000 -> 30000
A11: 8 | B11: Crockery with wash basin | C11: ='Sheet1 (1)'!I63 -> 73250 | D11: ='Sheet1 (1)'!K63 -> 69750 | E11: Clarity missing on sitting platform besides french window | F11: handing lamps | G11: 25500 | H11: =3*8000 -> 24000
A12: 9 | B12: Utility | C12: ='Sheet1 (1)'!I68 -> 99750 | D12: ='Sheet1 (1)'!K68 -> 95250 | E12: Wash basin shall be part of the quote | F12: Chimney | H12: 25000
A13: 10 | B13: Ceiling | C13: ='Sheet1 (1)'!I70 -> 162000 | D13: ='Sheet1 (1)'!K70 -> 176000 | E13: Excess SFT was considered in quote. Needs correction
A14: 11 | B14: Lighting | C14: ='Sheet1 (1)'!I76 -> 110900 | D14: ='Sheet1 (1)'!K76 -> 110900 | E14: Agreed as it is.
A15: 12 | B15: Curtains | C15: ='Sheet1 (1)'!I84 -> 90300 | D15: ='Sheet1 (1)'!K84 -> 90300 | E15: Price can be agreed but not part of Quote
A16: 13 | B16: Miscellaneous works | C16: ='Sheet1 (1)'!I89 -> 130000 | D16: ='Sheet1 (1)'!K89 -> 130000 | E16: Agreed as it is. | F16: TOTAL Furniture | G16: =SUM(G4:G15) -> 385500 | H16: =SUM(H4:H15) -> 286000
A17: 14
A18: 15
B19: TOTAL with curtains | C19: =SUM(C4:C18) -> 2302250 | D19: =SUM(D4:D16) -> 2027800
B20: TOTAL without curtains | C20: =C19-C15 -> 2211950 | D20: =D19-D15 -> 1937500 | E20: My final offer without curtains and without Furniture is 19.5 lakh
B21: Total with Furniture & Curtains | C21: =C19+G16 -> 2687750 | D21: =D19+H16 -> 2313800 | E21: Final offer without curtains and with Furniture is 22.5 akh
B22: Total with Furniture & W/O Curtains | C22: =C20+G16 -> 2597450 | D22: =D20+H16 -> 2223500
A24: Have removed Rs 1 lakh worth of original scope/requirement.

Sheet Sheet3 (1)
A1: Furniture
A2: MBR BED | E2: dimensions | F2: 6'x5'6" | G2: 45000 | H2: =G2 -> 45000 | I2: =H2 -> 45000
A3: dinning chairs | E3: nos | F3: 6 | G3: 15000 | H3: =F3*G3 -> 90000 | I3: =6*7500 -> 45000
A4: L shape sofa | E4: Dimension | F4: 11'x7'.5" | G4: 105000 | H4: =G4 -> 105000 | I4: =90000 -> 90000
A5: dressing chair | E5: nos | F5: 2 | G5: 13500 | H5: =F5*G5 -> 27000
A6: study chair | E6: nos | F6: 1 | G6: 10500 | H6: =F6*G6 -> 10500 | I6: =8000 -> 8000
A7: kitchen sink | E7: nos | F7: 2 | G7: 9500 | H7: =F7*G7 -> 19000 | I7: =H7 -> 19000
A8: Wash basin | E8: nos | F8: 1 | G8: 12500 | H8: =F8*G8 -> 12500
A9: Hanging swing chair | E9: nos | F9: 1 | G9: 35000 | H9: =F9*G9 -> 35000 | I9: =30000 -> 30000
A10: Dressing Mirrors | E10: nos | F10: 3 | G10: 18500 | H10: =F10*G10 -> 55500
A11: handing lamps | E11: nos | F11: 3 | G11: 8500 | H11: =F11*G11 -> 25500 | I11: 24000
A12: Chimney | I12: =25000 -> 25000
A13: Total | H13: =SUM(H2:H11) -> 425000 | I13: =SUM(I2:I12) -> 286000
